{"success":true,"courseCode":"20137-2025","courseName":"งานเครื่องจักรกลเก็บเกี่ยวอ้อย","courseNameEn":"Sugar Cane Harvest","credit":"1-3-2","deptName":"ช่างซ่อมบำรุงเครื่องจักรกลเกษตร","level":"ปวช.","standardRef":"-","learningOutcomes":"ซ่อมบ ารุงเครื่องเก็บเกี่ยวอ้อยเบื้องต้นโดยค านึงถึงความปลอดภัย","objectives":"1. เข้าใจหลักการเก็บเกี่ยวอ้อย\n2. สามารถปฏิบัติงานเก็บเกี่ยวผลผลิตอ้อย\n3. มีกิจนิสัยที่ดีในการท างาน รับผิดชอบ ประณีต รอบคอบ ตรงต่อเวลา สะอาด ปลอดภัย และรักษา\nสภาพแวดล้อม\n4. สามารถประยุกต์ใช้เครื่องมือในการซ่อมเครื่องเก็บเกี่ยวอ้อย\nสมรร นะรายวิชา\n1. แสดงความรู้เกี่ยวกับหลักการเก็บเกี่ยวอ้อย\n2. เก็บเกี่ยวผลผลิตอ้อย\n3. ประยุกต์ใช้เครื่องมือในการซ่อมบ ารุงเครื่องเก็บเกี่ยวอ้อย","competencies":"","description":"ศึกษาและปฏิบัติเกี่ยวกับ ส ารวจข้อมูลการเก็บเกี่ยวอ้อย วางแผนเก็บเกี่ยวอ้อย เตรียมเครื่อง\nเก็บเกี่ยวอ้อยก่อนใช้งาน เก็บเกี่ยวอ้อยโดยค านึงถึงความปลอดภัย","pdfPage":81,"pdfUrl":"https://bsq.vec.go.th/wp-content/uploads/sites/13/2026/03/20137v3.pdf#page=81"}