{"success":true,"courseCode":"20137-2013","courseName":"งานเครื่องจักรกลหลังการเก็บเกี่ยว","courseNameEn":"Post-harvest Machinery","credit":"1-3-2","deptName":"ช่างซ่อมบำรุงเครื่องจักรกลเกษตร","level":"ปวช.","standardRef":"-","learningOutcomes":"ใช้และบารุงรักษาเครื่องจักรกลเกษตรหลังการเก็บเกี่ยวด้วยความรอบคอบปลอดภัย","objectives":"1. เข้าใจหลักปฏิบัติหลังการเก็บเกี่ยวหลักการทางานของเครื่องจักรกลหลังการเก็บเกี่ยว\n2. สามารถใช้ บารุงรักษา เครื่องจักรกลหลังการเก็บเกี่ยว\n3. มีเจตคิต กิจนิสัยที่ดีในการทางานด้วยความรับผิดชอบ รอบคอบ ประหยัด ปลอดภัย ขยัน\nและอดทน โดยคานึงถึงผลกระทบต่อพลังงานและสิ่งแวดล้อม\n4. สามารถประยุกต์ใช้ความรู้ ทักษะ เครื่องมือ บารุงรักษา เครื่องจักรกลหลังการเก็บเกี่ยวตามคู่มือ\nการใช้งาน\nสมรร นะรายวิชา\n1. แสดงความรู้เกี่ยวกับหลักการทางานของเครื่องจักรกลหลังการเก็บเกี่ยว\n2. ควบคุมการใช้งานเครื่องจักรกลหลังการเก็บเกี่ยว\n3. ประยุกต์ใช้ความรู้ ทักษะ เครื่องมือ ซ่อม บารุงรักษา เครื่องจักรกลหลังการเก็บเกี่ยวตามคู่มือ","competencies":"","description":"ศึกษาและปฏิบัติเกี่ยวกับลักษณะทางกายภาพเบื้องต้น และหลักปฏิบัติที่ดีหลังการเก็บเกี่ยวผลผลิต\nเกษตร หลักการทางาน การใช้และบารุงรักษาเครื่องจักรกลเกษตรหลังการเก็บเกี่ยว","pdfPage":69,"pdfUrl":"https://bsq.vec.go.th/wp-content/uploads/sites/13/2026/03/20137v3.pdf#page=69"}