{"success":true,"courseCode":"21619-2005","courseName":"องค์ประกอบศิลป์เพื่องานนิเทศศิลป์","courseNameEn":"Composition for Communication Design","credit":"1-4-3","deptName":"ออกแบบนิเทศศิลป์","level":"ปวช.","standardRef":"-","learningOutcomes":"สามารถประยุกต์ใช้องค์ประกอบศิลป์เพื่องานนิเทศศิลป์ กับงานศิลปะและการออกแบบประเภทต่างๆ\nได้อย่างเหมาะสม","objectives":"1. เข้าใจหลักการออกแบบงานนิเทศศิลป์ ตามหลักองค์ประกอบศิลป์\n2. มีทักษะในการใช้เทคนิคออกแบบงานนิเทศศิลป์ ตามหลักองค์ประกอบศิลป์\n3. มีเจตคติและกิจนิสัยที่ดีในการปฏิบัติงานด้วยความรับผิดชอบ มุ่งมั่น สนใจใฝ่รู้ มีความคิดสร้างสรรค์\n4. ประยุกต์ใช้หลักการองค์ประกอบศิลป์เพื่องานนิเทศศิลป์ ในงานศิลปกรรมและงานออกแบบ\nประเภทต่างๆ","competencies":"1. แสดงความรู้เกี่ยวกับองค์ประกอบศิลป์เพื่องานนิเทศศิลป์\n2. ออกแบบงานนิเทศศิลป์ โดยใช้เทคนิคที่เหมาะสม","description":"ศึกษาและปฏิบัติการสร้างภาพ การจัดภาพ การประยุกต์ ตามหลักองค์ประกอบศิลป์ และทฤษฎีสี\nในงานออกแบบนิเทศศิลป์ ทั้ง 2,3 มิติ การสร้างสรรค์ภาพประกอบเรื่อง การออกแบบสื่อโฆษณา ด้วยวัสดุ\nและเทคนิคที่เหมาะสมกับท้องถิ่น ภูมิปัญญาไทยและสากล","pdfPage":65,"pdfUrl":"https://bsq.vec.go.th/wp-content/uploads/sites/13/2026/03/21619v2.pdf#page=65"}