{"success":true,"courseCode":"30118-2003","courseName":"การทดสอบวัสดุโดยทำลายสภาพ","courseNameEn":"Destructive testing","credit":"1-4-3","deptName":"การตรวจสอบโดยไม่ทำลาย","level":"ปวส.","standardRef":"-","learningOutcomes":"","objectives":"","competencies":"","description":"ศึกษาและปฏิบัติเกี่ยวกับ รหัส คำศัพท์เฉพาะ และสัญลักษณ์ต่างๆ ของการตรวจสอบโดย\nไม่ทำลายด้วยการตรวจสอบด้วยการตรวจพินิจ (VT) การตรวจสอบด้วยวิธีใช้สารแทรกซึม (PT)\nการตรวจสอบด้วยวิธีใช้ผงแม่เหล็ก (MT) การตรวจสอบด้วยคลื่นเสียงความถี่สูง (UT) การตรวจสอบด้วยวิธี\nสนามแม่เหล็กไฟฟ้า (ET) และการตรวจสอบด้วยวิธีถ่ายภาพรังีส (RT) เข้าใจหลักการรับรองบุคลากร\nการตรวจสอบโดยไม่ทำลายตามมาตรฐานสากล การจัดเตรียมเอกสาร ตรวจสอบ อ่านแบบสัญลักษณ์ และใช้\nเอกสารในงานการตรวจสอบโดยไม่ทำลาย การอ่านและเขียนขั้นตอนการปฏิบัติงาน (Procedure)\nรู้หลักเกณฑ์การเปรียบเทียบค่าของการตรวจสอบกับเกณฑ์มาตรฐานการยอมรับการตรวจสอบโดยไม่ทำลาย\nการบันทึกผลการปฏิบัติงานถูกต้องครบถ้วน และรายงานผลได้ตามข้อกำหนดของมาตรฐานการตรวจสอบ\nโดยไม่ทำลาย","pdfPage":64,"pdfUrl":"https://bsq.vec.go.th/wp-content/uploads/sites/13/2026/03/30118v4.pdf#page=64"}