{"success":true,"courseCode":"30135-2012","courseName":"เทคนิคการตรวจสอบคุณภาพงานซ่อมบำรุงเรือ","courseNameEn":"Technical Quality Control for Yacht Maintenance","credit":"1-2-2","deptName":"เทคนิคซ่อมบำรุงเรือ","level":"ปวส.","standardRef":"1. มาตรฐานอาชีพและคุณวุฒิวิชาชีพ หน่วยงาน สถาบันคุณวุฒิวิชาชีพ (องค์การมหาชน)\nอาชีพช่างต่อเรือ ระดับ 4","learningOutcomes":"ประยุกต์ใช้หลักการเทคนิคการตรวจสอบคุณภาพงานซ่อมบ ารุงเรือ ในงานอาชีพตามมาตรฐาน\nช่างซ่อมบ ารุงเรือยอร์ช","objectives":"1. เข้าใจหลักการและวิธีการควบคุมคุณภาพการซ่อมบ ารุงเรือยอร์ช\n2. สามารถใช้เทคนิคในการตรวจสอบคุณภาพงานซ่อมบ ารุงเรือตามลักษณะงาน\n3. มีกิจนิสัยที่ดีในการท างานด้วยความละเอียดรอบคอบ ปลอดภัย เป็นระเบียบ สะอาด ตรงต่อเวลา\nมีความซื่อสัตย์ รับผิดชอบ และรักษาสภาพแวดล้อม\n4. สามารถประยุกต์ใช้หลักการทางเทคนิคในการปฏิบัติงานตรวจสอบคุณภาพงานซ่อมบ ารุงเรือ\nสมรร นะรายวิชา\n1. ประมวลความรู้เกี่ยวหลักการควบคุมคุณภาพงานซ่อมบ ารุงเรือ\n2. ทักษะในวางแผนการควบคุมคุณภาพงานซ่อมบ ารุงเรือ\n3. เลือกใช้เครื่องมือในการตรวจสอบคุณภาพงานซ่อมบ ารุงเรือตามลักษณะงาน\n4. ประยุกต์ใช้หลักการทางเทคนิคในการแก้ไขปัญหาการตรวจสอบคุณภาพงานซ่อมบ ารุงเรือ","competencies":"","description":"ศึกษาและปฏิบัติเกี่ยวกับ ชิ้นส่วนโลหะที่ต้องตรวจสอบตามแบบ ตรวจสอบความถูกต้อง/สัดส่วนของ\nงานขยายแบบ ถ่ายแบบ และท าเทมเพลต (Template) ชิ้นส่วนเรือ ตรวจสอบชิ้นส่วนย่อย ระบุเครื่อง\nประกอบเรือตามแบบที่ต้องตรวจสอบตามแบบ ตรวจสอบความถูกต้อง/สัดส่วนของงานขยายแบบ ถ่ายแบบ\nและท าเทมเพลต (Template) ชิ้นส่วนเรือ ตรวจสอบชิ้นส่วนเครื่องประกอบเรือ","pdfPage":72,"pdfUrl":"https://bsq.vec.go.th/wp-content/uploads/sites/13/2026/03/30135v6.pdf#page=72"}