{"success":true,"courseCode":"31705-2008","courseName":"ปาราสัตในสัตว์","courseNameEn":"Parasitology in Animal","credit":"2–2-3","deptName":"สัตวรักษ์","level":"ปวส.","standardRef":"1. มาตรฐานวิชาชีพธุรกิจและบริการ รหัส 10204.02 อาชีพผู้ช่วยพยาบาลสัตว์ ระดับ 4\n2. มาตรฐานวิชาชีพธุรกิจและบริการ รหัส 10302.04 อาชีพนักเทคนิคการสัตวแพทย์ ระดับ 5\nผลลัพธ์การเรียนรู้ระดับ รายวิชา\nตรวจวิเคราะห์และรายงานผลการตรวจทางปาราสิตวิทยา\nจุดประสงค์รายวิชา เพื่อให้\n1. เข้าใจเกี่ยวกับประเภท ชนิด และการเกิดโรคของปาราสิต\n2. เตรียมอุปกรณ์ที่ใช้ในการตรวจสอบ วิเคราะห์ทางปาราสิต\n3. มีเจตคติและกิตนิสัยที่ดีต่อวิชาชีพและสังคม มีวินัย รับผิดชอบต่อตนเอง ต่อหน้าที่ และสามารถ\nทำงานร่วมกับผู้อื่นได้\n4. สามารถประยุกต์ใช้ความรู้และทักษะในการจัดการทางปาราสิตในสัตว์ได้","learningOutcomes":"","objectives":"","competencies":"1. ประมวลความรู้ในการจำแนกประเภท ชนิด และการเกิดโรคทางปาราสิต วางแผนป้องกันการเกิดโรคทางปาราสิต\nตามหลักการและกระบวนการ\n2. เลือก ใช้ เครื่องมือและอุปกรณ์ในการดูแลรักษาสัตว์จากโรคที่เกิดจากปาราสิต บันทึก รายงานผล\nตามหลักการและกระบวนการ\nคำอธิบายรายวิชา\nศึกษาและปฏิบัติเกี่ยวกับประเภทและชนิดของปาราสิต ตรวจวิเคราะห์ทางปาราสิต อ่านใบส่งตรวจและ\nตรวจสอบความถูกต้องสิ่งส่งตรวจตามใบสั่งตรวจของนายสัตวแพทย์ เตรียมอุปกรณ์ที่ใช้ตรวจสอบการตรวจวิเคราะห์\nทางปรสิตวิทยา ดำเนินการตรวจสิ่งส่งตรวจตามกระบวนการวิเคราะห์ทางปรสิตวิทยา รายงานผลตรวจวิเคราะห์\nทางปรสิตวิทยาทางห้องปฏิบัติการ","description":"","pdfPage":66,"pdfUrl":"https://bsq.vec.go.th/wp-content/uploads/sites/13/2026/03/31705v8.pdf#page=66"}