{"success":true,"courseCode":"31803-2019","courseName":"โครงงานด้านเทคโนโลยีเครื่องนุ่งห่ม 2","courseNameEn":"Clothing Technology Project 2","credit":"0-6-2","deptName":"เทคโนโลยีเครื่องนุ่งห่ม","level":"ปวส.","standardRef":"-","learningOutcomes":"","objectives":"","competencies":"1. ประมวลความรู้เกี่ยวกับ หลักการและกระบวนการวางแผน จัดทำโครงงาน ดำเนินงาน แก้ไข\nปัญหา ประเมินผล จัดทำรายงานและนำเสนอผลงาน\n2. เขียนโครงงานสร้างและหรือพัฒนางานตามหลักการ\n3. ดำเนินงานตามแผนงานโครงงานตามหลักการและกระบวนการ\n4. ประเมินผลการดำเนินงานโครงงานตามหลักการ\n5. รายงานผลการปฏิบัติงาน","description":"ศึกษาและปฏิบัติเกี่ยวกับ การจัดทำโครงงาน การวางแผน การดำเนินงาน การแก้ไขปัญหา\nการประเมินผล การจัดทำรายงานและการนำเสนอผลงาน โดยปฏิบัติจัดทำโครงงานสร้างและหรือพัฒนางาน\nตามลักษณะของงานให้แล้วเสร็จในระยะเวลาที่กำหนด","pdfPage":70,"pdfUrl":"https://bsq.vec.go.th/wp-content/uploads/sites/13/2026/03/31803v10.pdf#page=70"}